streamlit_custom_ydata_profiling/__init__.py
streamlit_custom_ydata_profiling/example.py
streamlit_custom_ydata_profiling/frontend/build/asset-manifest.json
streamlit_custom_ydata_profiling/frontend/build/bootstrap.min.css
streamlit_custom_ydata_profiling/frontend/build/index.html
streamlit_custom_ydata_profiling/frontend/build/static/js/main.a671263a.js
streamlit_custom_ydata_profiling/frontend/build/static/js/main.a671263a.js.LICENSE.txt
streamlit_custom_ydata_profiling-0.1.1.dist-info/LICENSE
streamlit_custom_ydata_profiling-0.1.1.dist-info/METADATA
streamlit_custom_ydata_profiling-0.1.1.dist-info/WHEEL
streamlit_custom_ydata_profiling-0.1.1.dist-info/top_level.txt
streamlit_custom_ydata_profiling-0.1.1.dist-info/RECORD
